setup.py
rk_udacity_distributions_package/Binomialdistribution.py
rk_udacity_distributions_package/Gaussiandistribution.py
rk_udacity_distributions_package/Generaldistribution.py
rk_udacity_distributions_package/__init__.py
rk_udacity_distributions_package.egg-info/PKG-INFO
rk_udacity_distributions_package.egg-info/SOURCES.txt
rk_udacity_distributions_package.egg-info/dependency_links.txt
rk_udacity_distributions_package.egg-info/not-zip-safe
rk_udacity_distributions_package.egg-info/top_level.txt