Metadata-Version: 1.0
Name: rk-udacity-distributions-package
Version: 1.0
Summary: Gaussian and Binomial distributions
Home-page: UNKNOWN
Author: Rohan Krishnakumar
Author-email: rohankrishnakumar3@gmail.com
License: UNKNOWN
Platform: UNKNOWN
